{
    "dogs": [
        {
            "name": "Champ",
            "color": "Red",
            "add_on_price": 39.56,
            "breed_id": 0,
            "url": "http://imgur.com/teSKsGF.jpg"
        },
        {
            "name": "Oliver",
            "color": "Poop_Colored",
            "add_on_price": 50.61,
            "breed_id": 3,
            "url": "http://imgur.com/hy1wM.jpg"
        },
        {
            "name": "Gracie",
            "color": "Green",
            "add_on_price": 49.94,
            "breed_id": 0,
            "url": "http://imgur.com/H0Ys0F4.jpg"
        },
        {
            "name": "Henry",
            "color": "Blue",
            "add_on_price": 41.51,
            "breed_id": 2,
            "url": "http://imgur.com/JMJemdh.jpg"
        },
        {
            "name": "Elvis",
            "color": "Black",
            "add_on_price": 7.26,
            "breed_id": 6,
            "url": "http://imgur.com/uPQD5.jpg"
        },
        {
            "name": "Ace",
            "color": "Green",
            "add_on_price": 4.05,
            "breed_id": 5,
            "url": "http://imgur.com/THB0EPk.jpg"
        },
        {
            "name": "Mimi",
            "color": "Orange",
            "add_on_price": 57.25,
            "breed_id": 0,
            "url": "http://imgur.com/io65WPF.jpg"
        },
        {
            "name": "Winnie",
            "color": "Blue",
            "add_on_price": 67.69,
            "breed_id": 4,
            "url": "http://imgur.com/Oxirlm3.jpg"
        },
        {
            "name": "Elvis",
            "color": "Orange",
            "add_on_price": 33.25,
            "breed_id": 1,
            "url": "http://imgur.com/amlib1p.jpg"
        },
        {
            "name": "Cleo",
            "color": "Poop_Colored",
            "add_on_price": 33.75,
            "breed_id": 6,
            "url": "http://imgur.com/22P70.jpg"
        },
        {
            "name": "Lily",
            "color": "Brown",
            "add_on_price": 18.63,
            "breed_id": 3,
            "url": "http://imgur.com/VPuIu.jpg"
        },
        {
            "name": "Stella",
            "color": "Brown",
            "add_on_price": 8.83,
            "breed_id": 4,
            "url": "http://imgur.com/14ow5EB.jpg"
        },
        {
            "name": "Brody",
            "color": "Purple",
            "add_on_price": 0.69,
            "breed_id": 6,
            "url": "http://imgur.com/TWfWMj5.jpg"
        },
        {
            "name": "Beau",
            "color": "Brown",
            "add_on_price": 33.87,
            "breed_id": 2,
            "url": "http://imgur.com/VPuIu.jpg"
        },
        {
            "name": "Cooper",
            "color": "Orange",
            "add_on_price": 63.65,
            "breed_id": 5,
            "url": "http://imgur.com/xpLJZVc.jpg"
        },
        {
            "name": "Milo",
            "color": "Blue",
            "add_on_price": 21.76,
            "breed_id": 2,
            "url": "http://imgur.com/ytxOrhM.jpg"
        },
        {
            "name": "Grace",
            "color": "Black",
            "add_on_price": 47.87,
            "breed_id": 0,
            "url": "http://imgur.com/EaaCQkI.jpg"
        },
        {
            "name": "Oreo",
            "color": "Purple",
            "add_on_price": 17.35,
            "breed_id": 2,
            "url": "http://imgur.com/n6hs0TZ.jpg"
        },
        {
            "name": "Mocha",
            "color": "Red",
            "add_on_price": 51.58,
            "breed_id": 3,
            "url": "http://imgur.com/R5vyXpw.jpg"
        },
        {
            "name": "Milo",
            "color": "Orange",
            "add_on_price": 52.66,
            "breed_id": 3,
            "url": "http://imgur.com/22P70.jpg"
        },
        {
            "name": "Chloe",
            "color": "Yellow",
            "add_on_price": 11.55,
            "breed_id": 6,
            "url": "http://imgur.com/46vFJ.jpg"
        },
        {
            "name": "Ginger",
            "color": "Black",
            "add_on_price": 56.84,
            "breed_id": 3,
            "url": "http://imgur.com/NvO0ASd.jpg"
        },
        {
            "name": "Elvis",
            "color": "Grey",
            "add_on_price": 39.14,
            "breed_id": 0,
            "url": "http://imgur.com/2imFL5v.jpg"
        },
        {
            "name": "Sparky",
            "color": "Orange",
            "add_on_price": 32.16,
            "breed_id": 3,
            "url": "http://imgur.com/HJdVR8b.jpg"
        },
        {
            "name": "Rufus",
            "color": "Purple",
            "add_on_price": 30.02,
            "breed_id": 5,
            "url": "http://imgur.com/iixtzvW.jpg"
        },
        {
            "name": "Dexter",
            "color": "Poop_Colored",
            "add_on_price": 51.94,
            "breed_id": 4,
            "url": "http://imgur.com/gIfofT3.jpg"
        },
        {
            "name": "Beau",
            "color": "Grey",
            "add_on_price": 64.22,
            "breed_id": 6,
            "url": "http://imgur.com/f9vwgyn.jpg"
        },
        {
            "name": "Rocky",
            "color": "Blue",
            "add_on_price": 21.91,
            "breed_id": 5,
            "url": "http://imgur.com/7WsW5qO.jpg"
        },
        {
            "name": "Mocha",
            "color": "Green",
            "add_on_price": 53.19,
            "breed_id": 3,
            "url": "http://imgur.com/NvO0ASd.jpg"
        },
        {
            "name": "Mac",
            "color": "Grey",
            "add_on_price": 50.83,
            "breed_id": 1,
            "url": "http://imgur.com/oBcyQRf.jpg"
        },
        {
            "name": "Allie",
            "color": "Green",
            "add_on_price": 5.74,
            "breed_id": 2,
            "url": "http://imgur.com/nuXAw1h.jpg"
        },
        {
            "name": "Riley",
            "color": "Green",
            "add_on_price": 64.8,
            "breed_id": 4,
            "url": "http://imgur.com/maiIg.jpg"
        },
        {
            "name": "Cleo",
            "color": "Poop_Colored",
            "add_on_price": 45.66,
            "breed_id": 3,
            "url": "http://imgur.com/cEZ0O9v.jpg"
        },
        {
            "name": "Simba",
            "color": "Grey",
            "add_on_price": 55.56,
            "breed_id": 5,
            "url": "http://imgur.com/oBcyQRf.jpg"
        },
        {
            "name": "Chase",
            "color": "Brown",
            "add_on_price": 66.03,
            "breed_id": 0,
            "url": "http://imgur.com/hy1wM.jpg"
        },
        {
            "name": "Ginger",
            "color": "Orange",
            "add_on_price": 59.68,
            "breed_id": 1,
            "url": "http://imgur.com/suNUuC4.jpg"
        },
        {
            "name": "Sassy",
            "color": "Brown",
            "add_on_price": 46.39,
            "breed_id": 2,
            "url": "http://imgur.com/PMpaTkD.jpg"
        },
        {
            "name": "Sadie",
            "color": "Brown",
            "add_on_price": 0.27,
            "breed_id": 5,
            "url": "http://imgur.com/GwEvkbs.jpg"
        },
        {
            "name": "Ollie",
            "color": "Blue",
            "add_on_price": 57.02,
            "breed_id": 6,
            "url": "http://imgur.com/IC4kus2.jpg"
        },
        {
            "name": "Bo",
            "color": "Brown",
            "add_on_price": 16.33,
            "breed_id": 3,
            "url": "http://imgur.com/MPY3ZuL.jpg"
        }
    ]
}